webfile/__init__.py
webfile-0.1.0.dist-info/LICENSE
webfile-0.1.0.dist-info/METADATA
webfile-0.1.0.dist-info/WHEEL
webfile-0.1.0.dist-info/top_level.txt
webfile-0.1.0.dist-info/RECORD
